aics_pipeline_uploaders/__init__.py
aics_pipeline_uploaders/celigo_uploader.py
aics_pipeline_uploaders/drug_uploader.py
aics_pipeline_uploaders/emt_uploader.py
aics_pipeline_uploaders/fms_uploader.py
aics_pipeline_uploaders/bin/__init__.py
aics_pipeline_uploaders/tests/__init__.py
aics_pipeline_uploaders/util/__init__.py
aics_pipeline_uploaders/util/celigo.py
aics_pipeline_uploaders/util/test/__init__.py
aics_pipeline_uploaders/util/test/test_celigo.py
aics_pipeline_uploaders-1.1.0.dist-info/LICENSE
aics_pipeline_uploaders-1.1.0.dist-info/METADATA
aics_pipeline_uploaders-1.1.0.dist-info/WHEEL
aics_pipeline_uploaders-1.1.0.dist-info/top_level.txt
aics_pipeline_uploaders-1.1.0.dist-info/RECORD
