Metadata-Version: 2.1
Name: aics-pipeline-uploaders
Version: 1.1.0
Summary: This package contains resources for uploading pipeline data to FMS
Author-email: AICS <!AICS_SW@alleninstitute.org>
Project-URL: homepage, https://github.com/aics-int/aics_pipeline_uploaders
Project-URL: documentation, https://aics-int.github.io/aics_pipeline_uploaders
Project-URL: repository, https://github.com/aics-int/aics_pipeline_uploaders
Requires-Python: >=3.9.2
License-File: LICENSE
Requires-Dist: aicsimageio (~=4.9.2)
Requires-Dist: aicsimageio[czi] (~=4.4)
Requires-Dist: aicsfiles (~=5.1.0)
Requires-Dist: lkaccess (~=1.4.25)
Provides-Extra: dev
Requires-Dist: black (==22.8.0) ; extra == 'dev'
Requires-Dist: build (==0.7.0) ; extra == 'dev'
Requires-Dist: bump2version (~=1.1.0) ; extra == 'dev'
Requires-Dist: flake8 (~=5.0.4) ; extra == 'dev'
Requires-Dist: furo (==2022.9.29) ; extra == 'dev'
Requires-Dist: isort (~=5.9) ; extra == 'dev'
Requires-Dist: m2r2 (~=0.3.3) ; extra == 'dev'
Requires-Dist: mypy (==0.982) ; extra == 'dev'
Requires-Dist: numpy (~=1.23.4) ; extra == 'dev'
Requires-Dist: pre-commit (~=2.20.0) ; extra == 'dev'
Requires-Dist: pytest (~=7.2.0) ; extra == 'dev'
Requires-Dist: requests-mock (~=1.10.0) ; extra == 'dev'
Requires-Dist: Sphinx (~=5.3.0) ; extra == 'dev'
Requires-Dist: tifffile (==2022.10.10) ; extra == 'dev'
Requires-Dist: twine (~=4.0.1) ; extra == 'dev'
Requires-Dist: types-python-dateutil (~=2.8.19) ; extra == 'dev'
Requires-Dist: types-requests (~=2.28.11) ; extra == 'dev'
Requires-Dist: wheel (~=0.37.0) ; extra == 'dev'
